remote_embed.py
setup.cfg
setup.py
remote_embed.egg-info/PKG-INFO
remote_embed.egg-info/SOURCES.txt
remote_embed.egg-info/dependency_links.txt
remote_embed.egg-info/top_level.txt