Metadata-Version: 1.1
Name: remote-embed
Version: 1.0.2
Summary: A remote version of code.interact()
Home-page: https://github.com/pandolia/remote_embed/
Author: pandolia
Author-email: pandolia@yeah.net
License: UNKNOWN
Download-URL: https://github.com/pandolia/remote_embed/archive/1.0.2.tar.gz
Keywords: python debug,python debugger,remote debug,remote debugger,code.interact,remote interact,interact
Platform: UNKNOWN
